LICENSE.txt
README.md
setup.cfg
setup.py
pyeit/__init__.py
pyeit.egg-info/PKG-INFO
pyeit.egg-info/SOURCES.txt
pyeit.egg-info/dependency_links.txt
pyeit.egg-info/not-zip-safe
pyeit.egg-info/requires.txt
pyeit.egg-info/top_level.txt
pyeit/eit/__init__.py
pyeit/eit/base.py
pyeit/eit/bp.py
pyeit/eit/fem.py
pyeit/eit/greit.py
pyeit/eit/interp2d.py
pyeit/eit/jac.py
pyeit/eit/protocol.py
pyeit/eit/render.py
pyeit/eit/svd.py
pyeit/eit/utils.py
pyeit/feature_extraction/__init__.py
pyeit/feature_extraction/dynamic_eit.py
pyeit/feature_extraction/mesh_geometry.py
pyeit/feature_extraction/transfer_impedance.py
pyeit/io/__init__.py
pyeit/io/daeger_eit.py
pyeit/io/et3.py
pyeit/io/et4.py
pyeit/io/ewd.py
pyeit/io/icp.py
pyeit/io/mes.py
pyeit/io/utils.py
pyeit/mesh/__init__.py
pyeit/mesh/distmesh.py
pyeit/mesh/external.py
pyeit/mesh/mesh_circle.py
pyeit/mesh/mesh_img.py
pyeit/mesh/plot_mesh.py
pyeit/mesh/quality.py
pyeit/mesh/shape.py
pyeit/mesh/shell.py
pyeit/mesh/utils.py
pyeit/mesh/wrapper.py
pyeit/mesh/plot/__init__.py
pyeit/mesh/plot/simconv.py
pyeit/mesh/plot/tetplot.py
pyeit/mesh/plot/tetshade.py
pyeit/mesh/plot/voronoi_plot.py
pyeit/preprocess/__init__.py
pyeit/quality/__init__.py
pyeit/quality/merit.py
pyeit/visual/__init__.py
pyeit/visual/plot.py